fi/evals/__init__.py
fi/evals/evaluator.py
fi/evals/llm/__init__.py
fi/evals/llm/base_llm_provider.py
fi/evals/llm/providers/litellm.py
fi/evals/metrics/__init__.py
fi/evals/metrics/base_llm_metric.py
fi/evals/metrics/base_metric.py
fi/evals/metrics/heuristics/aggregation_metrics.py
fi/evals/metrics/heuristics/json_metrics.py
fi/evals/metrics/heuristics/similarity_metrics.py
fi/evals/metrics/heuristics/string_metrics.py
fi/evals/metrics/llm_as_judges/__init__.py
fi/evals/metrics/llm_as_judges/custom_judge/metric.py
fi/evals/metrics/llm_as_judges/custom_judge/prompts.py
fi/evals/metrics/llm_as_judges/types.py
fi/evals/otel_utils.py
fi/evals/protect.py
fi/evals/protect_input_adapter.py
fi/evals/templates.py
fi/evals/types.py
ai_evaluation-0.2.2.dist-info/METADATA
ai_evaluation-0.2.2.dist-info/WHEEL
ai_evaluation-0.2.2.dist-info/RECORD
