Metadata-Version: 2.3
Name: ai-evaluation
Version: 0.2.2
Summary: We help GenAI teams maintain high-accuracy for their Models in production.
Author: Future AGI
Author-email: no-reply@futureagi.com
Requires-Python: >=3.10,<3.14
Classifier: Programming Language :: Python :: 3
Classifier: Programming Language :: Python :: 3.10
Classifier: Programming Language :: Python :: 3.11
Classifier: Programming Language :: Python :: 3.12
Classifier: Programming Language :: Python :: 3.13
Requires-Dist: futureagi (>=0.6.7)
Requires-Dist: jsonschema (>=4.25.1,<5.0.0)
Requires-Dist: litellm (>=1.77.4,<2.0.0)
Requires-Dist: openai (>=1.109.1,<2.0.0)
Requires-Dist: requests (>=2.32.5,<3.0.0)
